rapydmain/__init__.py
rapydmain/rapydmain.py
rapydmain-1.0.0.dist-info/LICENSE
rapydmain-1.0.0.dist-info/METADATA
rapydmain-1.0.0.dist-info/WHEEL
rapydmain-1.0.0.dist-info/top_level.txt
rapydmain-1.0.0.dist-info/RECORD
