Metadata-Version: 2.1
Name: rapydmain
Version: 1.0.0
Summary: rapydmain is framework for python batch script.
Home-page: https://github.com/aznuii
Author: aznuii
Author-email: aaz.nuii@gmail.com
License: MIT
Keywords: rapydmain
Platform: UNKNOWN
Classifier: License :: OSI Approved :: MIT License
Classifier: Programming Language :: Python :: 3.6
